pixanalyzer/__init__.py
pixanalyzer/__main__.py
pixanalyzer/main.py
pixanalyzer/threshold.py
pixanalyzer-0.2.0.dist-info/LICENSE
pixanalyzer-0.2.0.dist-info/METADATA
pixanalyzer-0.2.0.dist-info/WHEEL
pixanalyzer-0.2.0.dist-info/entry_points.txt
pixanalyzer-0.2.0.dist-info/top_level.txt
pixanalyzer-0.2.0.dist-info/RECORD
